nl2sql/__init__.py
nl2sql/cli.py
nl2sql/config.py
nl2sql/llm.py
nl2sql/tutorial_system.py
query_crafter_cli-0.1.0.dist-info/licenses/LICENSE
query_crafter_cli-0.1.0.dist-info/METADATA
query_crafter_cli-0.1.0.dist-info/WHEEL
query_crafter_cli-0.1.0.dist-info/entry_points.txt
query_crafter_cli-0.1.0.dist-info/top_level.txt
query_crafter_cli-0.1.0.dist-info/RECORD
