Metadata-Version: 2.4
Name: query-crafter-cli
Version: 0.1.0
Summary: CLI tool for natural language to any database query conversion
Author-email: Siddharth Patil <siddharthpatil0206@gmail.com>
License: MIT License
Requires-Python: >=3.10
License-File: LICENSE
Requires-Dist: click>=8.1.7
Requires-Dist: rich>=13.9.4
Requires-Dist: pyperclip>=1.9.0
Requires-Dist: openai>=1.102.0
Requires-Dist: requests>=2.32.5
Dynamic: license-file
